AUTHORS
LICENSE
MANIFEST.in
README.rst
setup.py
django_tastypie_migrate_fix.egg-info/PKG-INFO
django_tastypie_migrate_fix.egg-info/SOURCES.txt
django_tastypie_migrate_fix.egg-info/dependency_links.txt
django_tastypie_migrate_fix.egg-info/not-zip-safe
django_tastypie_migrate_fix.egg-info/requires.txt
django_tastypie_migrate_fix.egg-info/top_level.txt
docs/Makefile
docs/api.rst
docs/authentication.rst
docs/authorization.rst
docs/bundles.rst
docs/caching.rst
docs/compatibility_notes.rst
docs/conf.py
docs/content_types.rst
docs/contributing.rst
docs/cookbook.rst
docs/debugging.rst
docs/fields.rst
docs/geodjango.rst
docs/index.rst
docs/interacting.rst
docs/non_orm_data_sources.rst
docs/paginator.rst
docs/python3.rst
docs/resources.rst
docs/serialization.rst
docs/settings.rst
docs/testing.rst
docs/throttling.rst
docs/toc.rst
docs/tools.rst
docs/tutorial.rst
docs/validation.rst
docs/who_uses.rst
docs/release_notes/index.rst
docs/release_notes/v0.9.13.rst
docs/release_notes/v0.9.14.rst
docs/release_notes/v0.9.15.rst
tastypie/__init__.py
tastypie/admin.py
tastypie/api.py
tastypie/authentication.py
tastypie/authorization.py
tastypie/bundle.py
tastypie/cache.py
tastypie/compat.py
tastypie/constants.py
tastypie/exceptions.py
tastypie/fields.py
tastypie/http.py
tastypie/models.py
tastypie/paginator.py
tastypie/resources.py
tastypie/serializers.py
tastypie/test.py
tastypie/throttle.py
tastypie/validation.py
tastypie/contrib/__init__.py
tastypie/contrib/contenttypes/__init__.py
tastypie/contrib/contenttypes/fields.py
tastypie/contrib/contenttypes/resources.py
tastypie/contrib/gis/__init__.py
tastypie/contrib/gis/resources.py
tastypie/management/__init__.py
tastypie/management/commands/__init__.py
tastypie/management/commands/backfill_api_keys.py
tastypie/migrations/0001_initial.py
tastypie/migrations/0002_add_apikey_index.py
tastypie/migrations/__init__.py
tastypie/templates/tastypie/basic.html
tastypie/templates/tastypie/detail.html
tastypie/templates/tastypie/list.html
tastypie/utils/__init__.py
tastypie/utils/dict.py
tastypie/utils/formatting.py
tastypie/utils/mime.py
tastypie/utils/timezone.py
tastypie/utils/urls.py
tastypie/utils/validate_jsonp.py